sktime_legacy-0.3.1.dist-info/top_level.txt
sktime_legacy-0.3.1.dist-info/LICENSE
sktime_legacy-0.3.1.dist-info/RECORD
sktime_legacy-0.3.1.dist-info/WHEEL
sktime_legacy-0.3.1.dist-info/METADATA
sktime_legacy.libs/libgomp-f7e03b3e.so.1.0.0
sktime/__init__.py
sktime/pipeline.py
sktime/model_selection.py
sktime/setup.py
sktime/contrib/__init__.py
sktime/contrib/experiments.py
sktime/contrib/basic_benchmarking.py
sktime/contrib/tale_of_two_toolkits.py
sktime/contrib/distance_based/__init__.py
sktime/contrib/distance_based/ts_distance_measures.py
sktime/contrib/distance_based/elastic_ensemble_from_file.py
sktime/contrib/rotation_forest/__init__.py
sktime/contrib/rotation_forest/rotation_forest_reworked.py
sktime/contrib/rotation_forest/rotation_forest_dev.py
sktime/contrib/dictionary_based/__init__.py
sktime/contrib/dictionary_based/bop.py
sktime/classifiers/__init__.py
sktime/classifiers/base.py
sktime/classifiers/distance_based/__init__.py
sktime/classifiers/distance_based/elastic_ensemble.py
sktime/classifiers/distance_based/proximity_forest.py
sktime/classifiers/distance_based/time_series_neighbors.py
sktime/classifiers/distance_based/tests/test_proximity.py
sktime/classifiers/distance_based/tests/__init__.py
sktime/classifiers/compose/__init__.py
sktime/classifiers/compose/column_ensembler.py
sktime/classifiers/compose/ensemble.py
sktime/classifiers/compose/tests/__init__.py
sktime/classifiers/compose/tests/test_TimeSeriesForestClassifier.py
sktime/classifiers/compose/tests/test_columnensembler.py
sktime/classifiers/dictionary_based/__init__.py
sktime/classifiers/dictionary_based/boss.py
sktime/classifiers/shapelet_based/__init__.py
sktime/classifiers/shapelet_based/stc.py
sktime/classifiers/frequency_based/__init__.py
sktime/classifiers/frequency_based/rise.py
sktime/classifiers/interval_based/__init__.py
sktime/classifiers/interval_based/tsf.py
sktime/highlevel/__init__.py
sktime/highlevel/tasks.py
sktime/highlevel/strategies.py
sktime/highlevel/tests/__init__.py
sktime/highlevel/tests/test_tasks.py
sktime/highlevel/tests/test_TSCStrategy.py
sktime/highlevel/tests/test_ForecastingStrategy.py
