Metadata-Version: 2.1
Name: sktime-legacy
Version: 0.3.1
Summary: scikit-learn compatible toolbox for learning with time series/panel data
Home-page: https://github.com/alan-turing-institute/sktime
Maintainer: F. Király
Maintainer-email: fkiraly@turing.ac.uk
License: BSD-3-Clause
Download-URL: https://pypi.org/project/sktime/#files
Project-URL: Issue Tracker, https://github.com/alan-turing-institute/sktime/issues
Project-URL: Documentation, https://alan-turing-institute.github.io/sktime/
Project-URL: Source Code, https://github.com/alan-turing-institute/sktime
Platform: UNKNOWN
Classifier: Intended Audience :: Science/Research
Classifier: Intended Audience :: Developers
Classifier: License :: OSI Approved
Classifier: Programming Language :: Python
Classifier: Topic :: Software Development
Classifier: Topic :: Scientific/Engineering
Classifier: Operating System :: Microsoft :: Windows
Classifier: Operating System :: POSIX
Classifier: Operating System :: Unix
Classifier: Operating System :: MacOS
Classifier: Programming Language :: Python :: 3.6
Classifier: Programming Language :: Python :: 3.7
Requires-Python: >=3.6
Requires-Dist: numpy (>=1.17.0)
Requires-Dist: scipy (>=1.2.0)
Requires-Dist: scikit-learn (>=0.21.0)
Requires-Dist: pandas (>=0.23.0)
Requires-Dist: joblib (>=0.13)
Requires-Dist: scikit-posthocs (>=0.5.0)
Requires-Dist: statsmodels (>=0.9.0)
Provides-Extra: alldeps
Requires-Dist: tests ; extra == 'alldeps'
Requires-Dist: docs ; extra == 'alldeps'
